Workbook

Sheet Exec Summary
A1: Orion Cloud Systems, Inc. (ORCS) - DCF Valuation
A2: FCFF / WACC Discounted Cash Flow Model | Currency: USD (millions) | Industry: Enterprise Software / Cloud (SaaS) | Country: n/a
A4: Company Snapshot
A5: Current Share Price | B5: =WACC!$B$11
A6: Diluted Shares Outstanding | B6: =WACC!$B$12
A7: Market Capitalisation | B7: =WACC!$B$13
A9: Valuation Summary - Value per Share
A10: Scenario | B10: Value/Share | C10: Current Price | D10: Upside/(Downside) | E10: Terminal Growth
A11: Bear | B11: ='Scenario Summary'!B4 | C11: ='Scenario Summary'!C4 | D11: ='Scenario Summary'!D4 | E11: ='Scenario Summary'!H4
A12: Base | B12: ='Scenario Summary'!B5 | C12: ='Scenario Summary'!C5 | D12: ='Scenario Summary'!D5 | E12: ='Scenario Summary'!H5
A13: Bull | B13: ='Scenario Summary'!B6 | C13: ='Scenario Summary'!C6 | D13: ='Scenario Summary'!D6 | E13: ='Scenario Summary'!H6
A16: Cost of Capital
A17: WACC (Base Case) | B17: =WACC!$B$17
A18: Cost of Equity | B18: =WACC!$B$7
A19: Risk-Free Rate | B19: =WACC!$B$3
A20: Beta | B20: =WACC!$B$4
A22: Value-Driver Ranking (EV swing %, largest first)
A23: WACC (+/-1.0pp) | B23: 0.28728246
A24: Terminal Growth (+/-0.5pp) | B24: 0.10806834
A25: Terminal EBITDA Margin (+/-1.0pp) | B25: 0.085460768
A26: Revenue CAGR (+/-1.0pp/yr) | B26: 0.071502898
A27: Capex % of Revenue (+/-0.5pp) | B27: 0.05622419
A29: Model Integrity Score: 100/100 - Model ready for review

Sheet Historical IS
A1: Line Item | B1: FY2021 | C1: FY2022 | D1: FY2023 | E1: FY2024 | F1: FY2025 | G1: FY2026
A2: Revenue | B2: 520 | C2: 610 | D2: 705 | E2: 810 | F2: 930 | G2: 1060
A3: COGS | B3: -156 | C3: -179.95 | D3: -204.45 | E3: -230.85 | F3: -260.4 | G3: -291.5
A4: Gross Profit | B4: =B2+B3 | C4: =C2+C3 | D4: =D2+D3 | E4: =E2+E3 | F4: =F2+F3 | G4: =G2+G3
A5: Gross Margin % | B5: =IFERROR(B4/B2,0) | C5: =IFERROR(C4/C2,0) | D5: =IFERROR(D4/D2,0) | E5: =IFERROR(E4/E2,0) | F5: =IFERROR(F4/F2,0) | G5: =IFERROR(G4/G2,0)
A6: R&D | B6: -83.2 | C6: -94.55 | D6: -105.75 | E6: -117.45 | F6: -130.2 | G6: -143.1
A7: S&M | B7: -135.2 | C7: -152.5 | D7: -169.2 | E7: -190.35 | F7: -213.9 | G7: -238.5
A8: G&A | B8: -52 | C8: -57.95 | D8: -63.45 | E8: -70.47 | F8: -79.05 | G8: -87.98
A9: Other Opex | B9: 0 | C9: 0 | D9: 0 | E9: 0 | F9: 0 | G9: 0
A10: EBITDA | B10: =SUM(B4,B6:B9) | C10: =SUM(C4,C6:C9) | D10: =SUM(D4,D6:D9) | E10: =SUM(E4,E6:E9) | F10: =SUM(F4,F6:F9) | G10: =SUM(G4,G6:G9)
A11: EBITDA Margin % | B11: =IFERROR(B10/B2,0) | C11: =IFERROR(C10/C2,0) | D11: =IFERROR(D10/D2,0) | E11: =IFERROR(E10/E2,0) | F11: =IFERROR(F10/F2,0) | G11: =IFERROR(G10/G2,0)
A12: D&A | B12: -21.84 | C12: -25.01 | D12: -28.2 | E12: -31.59 | F12: -35.34 | G12: -39.22
A13: EBIT | B13: =B10+B12 | C13: =C10+C12 | D13: =D10+D12 | E13: =E10+E12 | F13: =F10+F12 | G13: =G10+G12
A14: EBIT Margin % | B14: =IFERROR(B13/B2,0) | C14: =IFERROR(C13/C2,0) | D14: =IFERROR(D13/D2,0) | E14: =IFERROR(E13/E2,0) | F14: =IFERROR(F13/F2,0) | G14: =IFERROR(G13/G2,0)
A15: Interest Expense | B15: -8 | C15: -9 | D15: -10 | E15: -11 | F15: -12 | G15: -13
A16: Other Below EBIT (net, non-operating) | B16: 0 | C16: 0 | D16: 0 | E16: 0 | F16: 0 | G16: 0
A17: Pre-Tax Income | B17: =B13+B15+B16 | C17: =C13+C15+C16 | D17: =D13+D15+D16 | E17: =E13+E15+E16 | F17: =F13+F15+F16 | G17: =G13+G15+G16
A18: Taxes | B18: -15.3024 | C18: -21.8496 | D18: -30.36775 | E18: -37.9896 | F18: -46.79085 | G18: -59.208
A19: Effective Tax Rate % | B19: =IFERROR(-B18/B17,0) | C19: =IFERROR(-C18/C17,0) | D19: =IFERROR(-D18/D17,0) | E19: =IFERROR(-E18/E17,0) | F19: =IFERROR(-F18/F17,0) | G19: =IFERROR(-G18/G17,0)
A20: Net Income | B20: =B17+B18 | C20: =C17+C18 | D20: =D17+D18 | E20: =E17+E18 | F20: =F17+F18 | G20: =G17+G18
A22: Revenue Growth % (YoY) | C22: =IFERROR(C2/B2-1,"") | D22: =IFERROR(D2/C2-1,"") | E22: =IFERROR(E2/D2-1,"") | F22: =IFERROR(F2/E2-1,"") | G22: =IFERROR(G2/F2-1,"")

Sheet Historical BS
A1: Line Item | B1: FY2021 | C1: FY2022 | D1: FY2023 | E1: FY2024 | F1: FY2025 | G1: FY2026
A2: Cash & Equivalents | B2: 200.9376 | C2: 268.091 | D2: 360.68325 | E2: 482.17965 | F2: 637.1258 | G2: 829.5718
A3: Marketable Securities | B3: 40 | C3: 40 | D3: 40 | E3: 40 | F3: 40 | G3: 40
A4: Accounts Receivable | B4: 75.4 | C4: 90.28 | D4: 105.75 | E4: 123.12 | F4: 143.22 | G4: 165.36
A5: Inventory | B5: 0 | C5: 0 | D5: 0 | E5: 0 | F5: 0 | G5: 0
A6: Other Current Assets | B6: 26 | C6: 30.5 | D6: 35.25 | E6: 40.5 | F6: 46.5 | G6: 53
A7: PP&E | B7: 216.76 | C7: 224.08 | D7: 232.54 | E7: 241.45 | F7: 251.68 | G7: 263.34
A8: Goodwill | B8: 180 | C8: 180 | D8: 180 | E8: 180 | F8: 180 | G8: 180
A9: Intangible Assets | B9: 45 | C9: 42 | D9: 40 | E9: 38 | F9: 36 | G9: 34
A10: Other Assets | B10: 15.6 | C10: 18.3 | D10: 21.15 | E10: 24.3 | F10: 27.9 | G10: 31.8
A11: Total Assets | B11: =SUM(B2:B10) | C11: =SUM(C2:C10) | D11: =SUM(D2:D10) | E11: =SUM(E2:E10) | F11: =SUM(F2:F10) | G11: =SUM(G2:G10)
A13: Accounts Payable | B13: 21.84 | C13: 25.193 | D13: 28.623 | E13: 32.319 | F13: 36.456 | G13: 40.81
A14: Accrued Liabilities | B14: 31.2 | C14: 36.6 | D14: 42.3 | E14: 48.6 | F14: 55.8 | G14: 63.6
A15: Short-Term Debt | B15: 20 | C15: 20 | D15: 20 | E15: 20 | F15: 20 | G15: 20
A16: Long-Term Debt | B16: 220 | C16: 215 | D16: 210 | E16: 205 | F16: 200 | G16: 195
A17: Lease Liabilities | B17: 45 | C17: 44 | D17: 43 | E17: 42 | F17: 41 | G17: 40
A18: Other Liabilities | B18: 20.8 | C18: 24.4 | D18: 28.2 | E18: 32.4 | F18: 37.2 | G18: 42.4
A19: Total Liabilities | B19: =SUM(B13:B18) | C19: =SUM(C13:C18) | D19: =SUM(D13:D18) | E19: =SUM(E13:E18) | F19: =SUM(F13:F18) | G19: =SUM(G13:G18)
A20: Shareholders' Equity | B20: 440.8576 | C20: 528.058 | D20: 643.25025 | E20: 789.23065 | F20: 971.9698 | G20: 1195.2618
A21: Total Liabilities + Equity | B21: =B19+B20 | C21: =C19+C20 | D21: =D19+D20 | E21: =E19+E20 | F21: =F19+F20 | G21: =G19+G20
A22: Balance Check (Assets − (Liab.+Equity)) | B22: =B11-B21 | C22: =C11-C21 | D22: =D11-D21 | E22: =E11-E21 | F22: =F11-F21 | G22: =G11-G21
A23: Should be ~0 for every year: confirms Assets = Liabilities + Equity ties out exactly.
A24: Total Debt (ST + LT) | B24: =B15+B16 | C24: =C15+C16 | D24: =D15+D16 | E24: =E15+E16 | F24: =F15+F16 | G24: =G15+G16
A25: Total Debt & Leases | B25: =B24+B17 | C25: =C24+C17 | D25: =D24+D17 | E25: =E24+E17 | F25: =F24+F17 | G25: =G24+G17
A26: Total Cash & Investments | B26: =B2+B3 | C26: =C2+C3 | D26: =D2+D3 | E26: =E2+E3 | F26: =F2+F3 | G26: =G2+G3
A27: Net Working Capital | B27: =(B4+B5+B6)-(B13+B14) | C27: =(C4+C5+C6)-(C13+C14) | D27: =(D4+D5+D6)-(D13+D14) | E27: =(E4+E5+E6)-(E13+E14) | F27: =(F4+F5+F6)-(F13+F14) | G27: =(G4+G5+G6)-(G13+G14)

Sheet Historical CF
A1: Line Item | B1: FY2021 | C1: FY2022 | D1: FY2023 | E1: FY2024 | F1: FY2025 | G1: FY2026
A2: Net Income | B2: 48.4576 | C2: 69.1904 | D2: 93.58225 | E2: 120.3004 | F2: 152.31915 | G2: 187.492
A3: D&A | B3: 21.84 | C3: 25.01 | D3: 28.2 | E3: 31.59 | F3: 35.34 | G3: 39.22
A4: Stock-Based Compensation | B4: 15.6 | C4: 18.91 | D4: 22.56 | E4: 26.73 | F4: 31.62 | G4: 37.1
A5: Other Non-Cash Items | B5: 2 | C5: 3 | D5: 2 | E5: 2 | F5: 2 | G5: 2
A6: (Increase)/Decrease in NWC | B6: -3.36 | C6: -10.627 | D6: -11.09 | E6: -12.624 | F6: -14.763 | G6: -16.486
A7: Cash Flow from Operations | B7: =SUM(B2:B6) | C7: =SUM(C2:C6) | D7: =SUM(D2:D6) | E7: =SUM(E2:E6) | F7: =SUM(F2:F6) | G7: =SUM(G2:G6)
A9: Capex | B9: -28.6 | C9: -32.33 | D9: -36.66 | E9: -40.5 | F9: -45.57 | G9: -50.88
A10: Acquisitions | B10: 0 | C10: 0 | D10: 0 | E10: 0 | F10: 0 | G10: 0
A11: Other Investing | B11: 0 | C11: 0 | D11: 0 | E11: 0 | F11: 0 | G11: 0
A12: Cash Flow from Investing | B12: =SUM(B9:B11) | C12: =SUM(C9:C11) | D12: =SUM(D9:D11) | E12: =SUM(E9:E11) | F12: =SUM(F9:F11) | G12: =SUM(G9:G11)
A14: Debt Issuance/(Repayment) | B14: -5 | C14: -6 | D14: -6 | E14: -6 | F14: -6 | G14: -6
A15: Equity Issuance/(Repurchase) | B15: 0 | C15: 0 | D15: 0 | E15: 0 | F15: 0 | G15: 0
A16: Dividends | B16: 0 | C16: 0 | D16: 0 | E16: 0 | F16: 0 | G16: 0
A17: Cash Flow from Financing | B17: =SUM(B14:B16) | C17: =SUM(C14:C16) | D17: =SUM(D14:D16) | E17: =SUM(E14:E16) | F17: =SUM(F14:F16) | G17: =SUM(G14:G16)
A19: Net Change in Cash | B19: =B7+B12+B17 | C19: =C7+C12+C17 | D19: =D7+D12+D17 | E19: =E7+E12+E17 | F19: =F7+F12+F17 | G19: =G7+G12+G17

Sheet Historical Analysis
A1: Metric | B1: FY2021 | C1: FY2022 | D1: FY2023 | E1: FY2024 | F1: FY2025 | G1: FY2026
A2: Revenue Growth % | B2: ='Historical IS'!B22 | C2: ='Historical IS'!C22 | D2: ='Historical IS'!D22 | E2: ='Historical IS'!E22 | F2: ='Historical IS'!F22 | G2: ='Historical IS'!G22
A3: Gross Margin % | B3: ='Historical IS'!B5 | C3: ='Historical IS'!C5 | D3: ='Historical IS'!D5 | E3: ='Historical IS'!E5 | F3: ='Historical IS'!F5 | G3: ='Historical IS'!G5
A4: EBITDA Margin % | B4: ='Historical IS'!B11 | C4: ='Historical IS'!C11 | D4: ='Historical IS'!D11 | E4: ='Historical IS'!E11 | F4: ='Historical IS'!F11 | G4: ='Historical IS'!G11
A5: EBIT Margin % | B5: ='Historical IS'!B14 | C5: ='Historical IS'!C14 | D5: ='Historical IS'!D14 | E5: ='Historical IS'!E14 | F5: ='Historical IS'!F14 | G5: ='Historical IS'!G14
A6: Net Margin % | B6: =IFERROR('Historical IS'!B20/'Historical IS'!B2,0) | C6: =IFERROR('Historical IS'!C20/'Historical IS'!C2,0) | D6: =IFERROR('Historical IS'!D20/'Historical IS'!D2,0) | E6: =IFERROR('Historical IS'!E20/'Historical IS'!E2,0) | F6: =IFERROR('Historical IS'!F20/'Historical IS'!F2,0) | G6: =IFERROR('Historical IS'!G20/'Historical IS'!G2,0)
A7: Tax Rate % | B7: ='Historical IS'!B19 | C7: ='Historical IS'!C19 | D7: ='Historical IS'!D19 | E7: ='Historical IS'!E19 | F7: ='Historical IS'!F19 | G7: ='Historical IS'!G19
A8: Capex % of Revenue | B8: =IFERROR(-'Historical CF'!B9/'Historical IS'!B2,0) | C8: =IFERROR(-'Historical CF'!C9/'Historical IS'!C2,0) | D8: =IFERROR(-'Historical CF'!D9/'Historical IS'!D2,0) | E8: =IFERROR(-'Historical CF'!E9/'Historical IS'!E2,0) | F8: =IFERROR(-'Historical CF'!F9/'Historical IS'!F2,0) | G8: =IFERROR(-'Historical CF'!G9/'Historical IS'!G2,0)
A9: D&A % of Revenue | B9: =IFERROR(-'Historical IS'!B12/'Historical IS'!B2,0) | C9: =IFERROR(-'Historical IS'!C12/'Historical IS'!C2,0) | D9: =IFERROR(-'Historical IS'!D12/'Historical IS'!D2,0) | E9: =IFERROR(-'Historical IS'!E12/'Historical IS'!E2,0) | F9: =IFERROR(-'Historical IS'!F12/'Historical IS'!F2,0) | G9: =IFERROR(-'Historical IS'!G12/'Historical IS'!G2,0)
A10: NWC % of Revenue | B10: =IFERROR('Historical BS'!B27/'Historical IS'!B2,0) | C10: =IFERROR('Historical BS'!C27/'Historical IS'!C2,0) | D10: =IFERROR('Historical BS'!D27/'Historical IS'!D2,0) | E10: =IFERROR('Historical BS'!E27/'Historical IS'!E2,0) | F10: =IFERROR('Historical BS'!F27/'Historical IS'!F2,0) | G10: =IFERROR('Historical BS'!G27/'Historical IS'!G2,0)
A11: NOPAT | B11: ='Historical IS'!B13*(1-'Historical IS'!B19) | C11: ='Historical IS'!C13*(1-'Historical IS'!C19) | D11: ='Historical IS'!D13*(1-'Historical IS'!D19) | E11: ='Historical IS'!E13*(1-'Historical IS'!E19) | F11: ='Historical IS'!F13*(1-'Historical IS'!F19) | G11: ='Historical IS'!G13*(1-'Historical IS'!G19)
A12: Unlevered FCF | B12: =B11-'Historical IS'!B12+'Historical CF'!B9+'Historical CF'!B6 | C12: =C11-'Historical IS'!C12+'Historical CF'!C9+'Historical CF'!C6 | D12: =D11-'Historical IS'!D12+'Historical CF'!D9+'Historical CF'!D6 | E12: =E11-'Historical IS'!E12+'Historical CF'!E9+'Historical CF'!E6 | F12: =F11-'Historical IS'!F12+'Historical CF'!F9+'Historical CF'!F6 | G12: =G11-'Historical IS'!G12+'Historical CF'!G9+'Historical CF'!G6
A13: FCF Margin % | B13: =IFERROR(B12/'Historical IS'!B2,0) | C13: =IFERROR(C12/'Historical IS'!C2,0) | D13: =IFERROR(D12/'Historical IS'!D2,0) | E13: =IFERROR(E12/'Historical IS'!E2,0) | F13: =IFERROR(F12/'Historical IS'!F2,0) | G13: =IFERROR(G12/'Historical IS'!G2,0)
A16: Revenue CAGR (3Y) | B16: =IFERROR(('Historical IS'!G2/'Historical IS'!D2)^(1/3)-1,"")
A17: Revenue CAGR (5Y) | B17: =IFERROR(('Historical IS'!G2/'Historical IS'!B2)^(1/5)-1,"")
A19: Trend Commentary
A20: Revenue grew at a 15.3% 5-year CAGR (FY2021-FY2026), versus a 14.4% average over the most recent two years, indicating deceleration.
A21: EBITDA margin expanded from 18.0% in FY2021 to 28.2% in FY2026.
A22: Average Capex was 5.1% of revenue and average D&A was 4.0% of revenue over the historical period.

Sheet WACC
A1: Weighted Average Cost of Capital (WACC)
A2: Input | B2: Value | C2: Source | D2: Rationale
A3: Risk-Free Rate % | B3: 0.042 | C3: AssumptionSource.MARKET_DATA | D3: 10-year government bond yield as of the source date.
A4: Beta | B4: 1.15 | C4: AssumptionSource.MARKET_DATA | D4: 5-year weekly regression beta vs. broad market index (illustrative demo value).
A5: Equity Risk Premium % | B5: 0.055 | C5: AssumptionSource.MARKET_DATA | D5: Long-run historical equity risk premium for the company's market.
A6: Size Premium % | B6: 0 | C6: AssumptionSource.CALCULATED | D6: No size premium applied.
A7: Cost of Equity % = Rf + Beta × ERP + Size Prem. | B7: =B3+B4*B5+B6 | C7: calculated | D7: Rf + Beta x ERP + Size Premium
A8: Pre-Tax Cost of Debt % | B8: 0.058 | C8: AssumptionSource.MARKET_DATA | D8: Based on the company's current borrowing rate / comparable credit spread.
A9: Tax Rate % | B9: 0.24 | C9: AssumptionSource.HISTORICAL_ACTUAL | D9: Historical effective tax rate used as a proxy for the marginal rate.
A10: After-Tax Cost of Debt % = Kd × (1 − Tax) | B10: =B8*(1-B9) | C10: calculated | D10: Pre-Tax Cost of Debt x (1 - Tax Rate)
A11: Current Share Price | B11: 62.5 | C11: market_data | D11: Latest traded price.
A12: Diluted Shares Outstanding | B12: 115 | C12: market_data | D12: Diluted share count.
A13: Market Value of Equity = Price × Shares | B13: =B11*B12 | C13: calculated | D13: Current Share Price x Diluted Shares Outstanding.
A14: Market Value of Debt | B14: 255 | C14: AssumptionSource.HISTORICAL_ACTUAL | D14: Book value of total debt used as a proxy for market value of debt.
A15: Equity Weight % = E / (E+D) | B15: =B13/(B13+B14) | C15: calculated | D15: E / (D+E)
A16: Debt Weight % = D / (E+D) | B16: =1-B15 | C16: calculated | D16: D / (D+E)
A17: WACC % = We×Ke + Wd×Kd(1−t) | B17: =B15*B7+B16*B10 | C17: calculated | D17: We x Ke + Wd x Kd(1-t)

Sheet Forecast & FCFF (Base)
A1: Forecast & FCFF - Base Case | H1: Rationale (final forecast year)
A3: Metric | B3: FY2027 | C3: FY2028 | D3: FY2029 | E3: FY2030 | F3: FY2031
A4: Revenue Growth % | B4: 0.14396655 | C4: 0.11797491 | D4: 0.091983274 | E4: 0.065991637 | F4: 0.04 | H4: FY2031 revenue growth is assumed at 4.0%, glided from the recent 14.4% run-rate toward a 4.0% long-term normalized rate over the 5-year forecast horizon (vs. 15.3% historical 5-year CAGR), reflecting expected growth normalization.
A5: Revenue | B5: ='Historical IS'!G$2*(1+B4) | C5: =B5*(1+C4) | D5: =C5*(1+D4) | E5: =D5*(1+E4) | F5: =E5*(1+F4)
A6: Gross Margin % | B6: 0.725 | C6: 0.725 | D6: 0.725 | E6: 0.725 | F6: 0.725 | H6: FY2031 gross margin held at the last actual level of 72.5% (FY2026), consistent with the historical average of 71.2%.
A7: Gross Profit | B7: =B5*B6 | C7: =C5*C6 | D7: =D5*D6 | E7: =E5*E6 | F7: =F5*F6
A8: R&D % of Revenue | B8: 0.135 | C8: 0.135 | D8: 0.135 | E8: 0.135 | F8: 0.135 | H8: R&D % of Revenue modeled at 13.5% of revenue in FY2031, gliding from 13.5% (FY2026 actual) toward 13.5% as the model assumes operating leverage improves EBITDA margin toward 28.2% by FY2031.
A9: S&M % of Revenue | B9: 0.225 | C9: 0.225 | D9: 0.225 | E9: 0.225 | F9: 0.225 | H9: S&M % of Revenue modeled at 22.5% of revenue in FY2031, gliding from 22.5% (FY2026 actual) toward 22.5% as the model assumes operating leverage improves EBITDA margin toward 28.2% by FY2031.
A10: G&A % of Revenue | B10: 0.083 | C10: 0.083 | D10: 0.083 | E10: 0.083 | F10: 0.083 | H10: G&A % of Revenue modeled at 8.3% of revenue in FY2031, gliding from 8.3% (FY2026 actual) toward 8.3% as the model assumes operating leverage improves EBITDA margin toward 28.2% by FY2031.
A11: R&D | B11: =B5*B8 | C11: =C5*C8 | D11: =D5*D8 | E11: =E5*E8 | F11: =F5*F8
A12: S&M | B12: =B5*B9 | C12: =C5*C9 | D12: =D5*D9 | E12: =E5*E9 | F12: =F5*F9
A13: G&A | B13: =B5*B10 | C13: =C5*C10 | D13: =D5*D10 | E13: =E5*E10 | F13: =F5*F10
A14: Total Opex (ex D&A) | B14: =SUM(B11:B13) | C14: =SUM(C11:C13) | D14: =SUM(D11:D13) | E14: =SUM(E11:E13) | F14: =SUM(F11:F13)
A15: EBITDA | B15: =B7-B14 | C15: =C7-C14 | D15: =D7-D14 | E15: =E7-E14 | F15: =F7-F14
A16: EBITDA Margin % | B16: =IFERROR(B15/B5,0) | C16: =IFERROR(C15/C5,0) | D16: =IFERROR(D15/D5,0) | E16: =IFERROR(E15/E5,0) | F16: =IFERROR(F15/F5,0)
A17: D&A % of Revenue | B17: 0.0395 | C17: 0.0395 | D17: 0.0395 | E17: 0.0395 | F17: 0.0395 | H17: D&A modeled at the 4.0% historical average of revenue, held flat given no disclosed capex step-change.
A18: D&A | B18: =B5*B17 | C18: =C5*C17 | D18: =D5*D17 | E18: =E5*E17 | F18: =F5*F17
A19: EBIT | B19: =B15-B18 | C19: =C15-C18 | D19: =D15-D18 | E19: =E15-E18 | F19: =F15-F18
A20: EBIT Margin % | B20: =IFERROR(B19/B5,0) | C20: =IFERROR(C19/C5,0) | D20: =IFERROR(D19/D5,0) | E20: =IFERROR(E19/E5,0) | F20: =IFERROR(F19/F5,0)
A21: Tax Rate % | B21: 0.24 | C21: 0.24 | D21: 0.24 | E21: 0.24 | F21: 0.24 | H21: Tax rate held at the 24.0% historical average effective rate.
A22: Taxes on EBIT | B22: =MAX(B19,0)*B21 | C22: =MAX(C19,0)*C21 | D22: =MAX(D19,0)*D21 | E22: =MAX(E19,0)*E21 | F22: =MAX(F19,0)*F21
A23: NOPAT | B23: =B19-B22 | C23: =C19-C22 | D23: =D19-D22 | E23: =E19-E22 | F23: =F19-F22
A24: Capex % of Revenue | B24: 0.051166667 | C24: 0.04825 | D24: 0.045333333 | E24: 0.042416667 | F24: 0.0395 | H24: Capex modeled at 4.0% of revenue in FY2031, gliding from the 5.1% recent historical average (vs. 4.8% in the most recent year) toward 4.0% - the historical D&A % of revenue - by FY2031, reflecting the standard DCF assumption that reinvestment normalizes to roughly track depreciation once the business settles into the stable long-run growth priced into the terminal value.
A25: Capex | B25: =B5*B24 | C25: =C5*C24 | D25: =D5*D24 | E25: =E5*E24 | F25: =F5*F24
A26: NWC % of Revenue | B26: 0.10058333 | C26: 0.10058333 | D26: 0.10058333 | E26: 0.10058333 | F26: 0.10058333 | H26: Net working capital modeled at the 10.1% historical average of revenue, held constant given no evidence of a structural change in payment terms.
A27: Net Working Capital | B27: =B5*B26 | C27: =C5*C26 | D27: =D5*D26 | E27: =E5*E26 | F27: =F5*F26
A28: Change in NWC | B28: =B27-'Historical BS'!G$27 | C28: =C27-B27 | D28: =D27-C27 | E28: =E27-D27 | F28: =F27-E27
A29: FCFF = NOPAT + D&A − Capex − ΔNWC | B29: =B23+B18-B25-B28 | C29: =C23+C18-C25-C28 | D29: =D23+D18-D25-D28 | E29: =E23+E18-E25-E28 | F29: =F23+F18-F25-F28
A30: Discount Period (n) | B30: 1 | C30: 2 | D30: 3 | E30: 4 | F30: 5
A31: Discount Factor = 1/(1+WACC)^n | B31: =1/(1+WACC!$B$17)^B30 | C31: =1/(1+WACC!$B$17)^C30 | D31: =1/(1+WACC!$B$17)^D30 | E31: =1/(1+WACC!$B$17)^E30 | F31: =1/(1+WACC!$B$17)^F30
A32: PV of FCFF | B32: =B29*B31 | C32: =C29*C31 | D32: =D29*D31 | E32: =E29*E31 | F32: =F29*F31

Sheet DCF (Base)
A1: Discounted Cash Flow - Base Case
A3: Sum of PV of Explicit-Period FCFF | B3: =SUMPRODUCT('Forecast & FCFF (Base)'!B29:F29,'Forecast & FCFF (Base)'!B31:F31)
A4: Terminal Growth Rate (g) | B4: 0.03
A5: Terminal FCFF = Final-Year FCFF × (1+g) | B5: ='Forecast & FCFF (Base)'!F29*(1+B4)
A6: Terminal Value (Gordon Growth) = TFCFF/(WACC−g) | B6: =B5/(WACC!$B$17-B4)
A7: PV of Terminal Value | B7: =B6*'Forecast & FCFF (Base)'!F31
A8: Enterprise Value | B8: =B3+B7
A9: Terminal Value % of Enterprise Value | B9: =IFERROR(B7/B8,0)
A10: Exit Multiple (x EBITDA, cross-check) | B10: 14
A11: Terminal Value (Exit Multiple, memo) | B11: ='Forecast & FCFF (Base)'!F15*B10
A13: Enterprise Value → Equity Value Bridge
A14: Enterprise Value | B14: =B8
A15: + Cash & Investments | B15: 869.5718
A16: − Total Debt | B16: -215
A17: − Lease Liabilities | B17: -40
A18: − Minority Interest | B18: 0
A19: − Preferred Stock | B19: 0
A20: Equity Value | B20: =B14+SUM(B15:B19)
A21: Diluted Shares Outstanding | B21: 115
A22: Equity Value per Share | B22: =IFERROR(B20/B21,0)
A23: Current Share Price | B23: 62.5
A24: Upside / (Downside) % | B24: =IFERROR(B22/B23-1,0)

Sheet Forecast & FCFF (Bear)
A1: Forecast & FCFF | H1: Rationale (final forecast year)
A2: Scenario Cost of Capital (this tab's own WACC, applied to discounting below)
A3: Base-Case WACC (live link) | B3: =WACC!$B$17
A4: Scenario WACC = Base WACC + Delta | B4: =B3+(0.01)
A6: Metric | B6: FY2027 | C6: FY2028 | D6: FY2029 | E6: FY2030 | F6: FY2031
A7: Revenue Growth % | B7: 0.12396655 | C7: 0.09797491 | D7: 0.071983274 | E7: 0.045991637 | F7: 0.02 | H7: [Bear Case] FY2031 revenue growth is assumed at 4.0%, glided from the recent 14.4% run-rate toward a 4.0% long-term normalized rate over the 5-year forecast horizon (vs. 15.3% historical 5-year CAGR), reflecting expected growth normalization. Adjusted by -2.0% vs. Base Case.
A8: Revenue | B8: ='Historical IS'!G$2*(1+B7) | C8: =B8*(1+C7) | D8: =C8*(1+D7) | E8: =D8*(1+E7) | F8: =E8*(1+F7)
A9: Gross Margin % | B9: 0.725 | C9: 0.725 | D9: 0.725 | E9: 0.725 | F9: 0.725 | H9: FY2031 gross margin held at the last actual level of 72.5% (FY2026), consistent with the historical average of 71.2%.
A10: Gross Profit | B10: =B8*B9 | C10: =C8*C9 | D10: =D8*D9 | E10: =E8*E9 | F10: =F8*F9
A11: R&D % of Revenue | B11: 0.14166667 | C11: 0.14166667 | D11: 0.14166667 | E11: 0.14166667 | F11: 0.14166667 | H11: [Bear Case] R&D % of Revenue modeled at 13.5% of revenue in FY2031, gliding from 13.5% (FY2026 actual) toward 13.5% as the model assumes operating leverage improves EBITDA margin toward 28.2% by FY2031. Adjusted by +0.7% vs. Base Case.
A12: S&M % of Revenue | B12: 0.23166667 | C12: 0.23166667 | D12: 0.23166667 | E12: 0.23166667 | F12: 0.23166667 | H12: [Bear Case] S&M % of Revenue modeled at 22.5% of revenue in FY2031, gliding from 22.5% (FY2026 actual) toward 22.5% as the model assumes operating leverage improves EBITDA margin toward 28.2% by FY2031. Adjusted by +0.7% vs. Base Case.
A13: G&A % of Revenue | B13: 0.089666667 | C13: 0.089666667 | D13: 0.089666667 | E13: 0.089666667 | F13: 0.089666667 | H13: [Bear Case] G&A % of Revenue modeled at 8.3% of revenue in FY2031, gliding from 8.3% (FY2026 actual) toward 8.3% as the model assumes operating leverage improves EBITDA margin toward 28.2% by FY2031. Adjusted by +0.7% vs. Base Case.
A14: R&D | B14: =B8*B11 | C14: =C8*C11 | D14: =D8*D11 | E14: =E8*E11 | F14: =F8*F11
A15: S&M | B15: =B8*B12 | C15: =C8*C12 | D15: =D8*D12 | E15: =E8*E12 | F15: =F8*F12
A16: G&A | B16: =B8*B13 | C16: =C8*C13 | D16: =D8*D13 | E16: =E8*E13 | F16: =F8*F13
A17: Total Opex (ex D&A) | B17: =SUM(B14:B16) | C17: =SUM(C14:C16) | D17: =SUM(D14:D16) | E17: =SUM(E14:E16) | F17: =SUM(F14:F16)
A18: EBITDA | B18: =B10-B17 | C18: =C10-C17 | D18: =D10-D17 | E18: =E10-E17 | F18: =F10-F17
A19: EBITDA Margin % | B19: =IFERROR(B18/B8,0) | C19: =IFERROR(C18/C8,0) | D19: =IFERROR(D18/D8,0) | E19: =IFERROR(E18/E8,0) | F19: =IFERROR(F18/F8,0)
A20: D&A % of Revenue | B20: 0.0395 | C20: 0.0395 | D20: 0.0395 | E20: 0.0395 | F20: 0.0395 | H20: D&A modeled at the 4.0% historical average of revenue, held flat given no disclosed capex step-change.
A21: D&A | B21: =B8*B20 | C21: =C8*C20 | D21: =D8*D20 | E21: =E8*E20 | F21: =F8*F20
A22: EBIT | B22: =B18-B21 | C22: =C18-C21 | D22: =D18-D21 | E22: =E18-E21 | F22: =F18-F21
A23: EBIT Margin % | B23: =IFERROR(B22/B8,0) | C23: =IFERROR(C22/C8,0) | D23: =IFERROR(D22/D8,0) | E23: =IFERROR(E22/E8,0) | F23: =IFERROR(F22/F8,0)
A24: Tax Rate % | B24: 0.24 | C24: 0.24 | D24: 0.24 | E24: 0.24 | F24: 0.24 | H24: Tax rate held at the 24.0% historical average effective rate.
A25: Taxes on EBIT | B25: =MAX(B22,0)*B24 | C25: =MAX(C22,0)*C24 | D25: =MAX(D22,0)*D24 | E25: =MAX(E22,0)*E24 | F25: =MAX(F22,0)*F24
A26: NOPAT | B26: =B22-B25 | C26: =C22-C25 | D26: =D22-D25 | E26: =E22-E25 | F26: =F22-F25
A27: Capex % of Revenue | B27: 0.056166667 | C27: 0.05325 | D27: 0.050333333 | E27: 0.047416667 | F27: 0.0445 | H27: [Bear Case] Capex modeled at 4.0% of revenue in FY2031, gliding from the 5.1% recent historical average (vs. 4.8% in the most recent year) toward 4.0% - the historical D&A % of revenue - by FY2031, reflecting the standard DCF assumption that reinvestment normalizes to roughly track depreciation once the business settles into the stable long-run growth priced into the terminal value. Adjusted by +0.5% vs. Base Case.
A28: Capex | B28: =B8*B27 | C28: =C8*C27 | D28: =D8*D27 | E28: =E8*E27 | F28: =F8*F27
A29: NWC % of Revenue | B29: 0.10558333 | C29: 0.10558333 | D29: 0.10558333 | E29: 0.10558333 | F29: 0.10558333 | H29: [Bear Case] Net working capital modeled at the 10.1% historical average of revenue, held constant given no evidence of a structural change in payment terms. Adjusted by +0.5% vs. Base Case.
A30: Net Working Capital | B30: =B8*B29 | C30: =C8*C29 | D30: =D8*D29 | E30: =E8*E29 | F30: =F8*F29
A31: Change in NWC | B31: =B30-'Historical BS'!G$27 | C31: =C30-B30 | D31: =D30-C30 | E31: =E30-D30 | F31: =F30-E30
A32: FCFF = NOPAT + D&A − Capex − ΔNWC | B32: =B26+B21-B28-B31 | C32: =C26+C21-C28-C31 | D32: =D26+D21-D28-D31 | E32: =E26+E21-E28-E31 | F32: =F26+F21-F28-F31
A33: Discount Period (n) | B33: 1 | C33: 2 | D33: 3 | E33: 4 | F33: 5
A34: Discount Factor = 1/(1+WACC)^n | B34: =1/(1+$B$4)^B33 | C34: =1/(1+$B$4)^C33 | D34: =1/(1+$B$4)^D33 | E34: =1/(1+$B$4)^E33 | F34: =1/(1+$B$4)^F33
A35: PV of FCFF | B35: =B32*B34 | C35: =C32*C34 | D35: =D32*D34 | E35: =E32*E34 | F35: =F32*F34

Sheet DCF (Bear)
A1: Discounted Cash Flow - Bear Case
A3: Sum of PV of Explicit-Period FCFF | B3: =SUMPRODUCT('Forecast & FCFF (Bear)'!B32:F32,'Forecast & FCFF (Bear)'!B34:F34)
A4: Base-Case Terminal g (live link) + Scenario Delta | B4: ='DCF (Base)'!$B$4+(-0.005)
A5: Terminal FCFF = Final-Year FCFF × (1+g) | B5: ='Forecast & FCFF (Bear)'!F32*(1+B4)
A6: Terminal Value (Gordon Growth) = TFCFF/(WACC−g) | B6: =B5/('Forecast & FCFF (Bear)'!$B$4-B4)
A7: PV of Terminal Value | B7: =B6*'Forecast & FCFF (Bear)'!F34
A8: Enterprise Value | B8: =B3+B7
A9: Terminal Value % of Enterprise Value | B9: =IFERROR(B7/B8,0)
A10: Exit Multiple (x EBITDA, cross-check) | B10: 14
A11: Terminal Value (Exit Multiple, memo) | B11: ='Forecast & FCFF (Bear)'!F18*B10
A13: Enterprise Value → Equity Value Bridge
A14: Enterprise Value | B14: =B8
A15: + Cash & Investments | B15: 869.5718
A16: − Total Debt | B16: -215
A17: − Lease Liabilities | B17: -40
A18: − Minority Interest | B18: 0
A19: − Preferred Stock | B19: 0
A20: Equity Value | B20: =B14+SUM(B15:B19)
A21: Diluted Shares Outstanding | B21: 115
A22: Equity Value per Share | B22: =IFERROR(B20/B21,0)
A23: Current Share Price | B23: 62.5
A24: Upside / (Downside) % | B24: =IFERROR(B22/B23-1,0)

Sheet Forecast & FCFF (Bull)
A1: Forecast & FCFF | H1: Rationale (final forecast year)
A2: Scenario Cost of Capital (this tab's own WACC, applied to discounting below)
A3: Base-Case WACC (live link) | B3: =WACC!$B$17
A4: Scenario WACC = Base WACC + Delta | B4: =B3+(-0.005)
A6: Metric | B6: FY2027 | C6: FY2028 | D6: FY2029 | E6: FY2030 | F6: FY2031
A7: Revenue Growth % | B7: 0.16396655 | C7: 0.13797491 | D7: 0.11198327 | E7: 0.085991637 | F7: 0.06 | H7: [Bull Case] FY2031 revenue growth is assumed at 4.0%, glided from the recent 14.4% run-rate toward a 4.0% long-term normalized rate over the 5-year forecast horizon (vs. 15.3% historical 5-year CAGR), reflecting expected growth normalization. Adjusted by +2.0% vs. Base Case.
A8: Revenue | B8: ='Historical IS'!G$2*(1+B7) | C8: =B8*(1+C7) | D8: =C8*(1+D7) | E8: =D8*(1+E7) | F8: =E8*(1+F7)
A9: Gross Margin % | B9: 0.725 | C9: 0.725 | D9: 0.725 | E9: 0.725 | F9: 0.725 | H9: FY2031 gross margin held at the last actual level of 72.5% (FY2026), consistent with the historical average of 71.2%.
A10: Gross Profit | B10: =B8*B9 | C10: =C8*C9 | D10: =D8*D9 | E10: =E8*E9 | F10: =F8*F9
A11: R&D % of Revenue | B11: 0.12833333 | C11: 0.12833333 | D11: 0.12833333 | E11: 0.12833333 | F11: 0.12833333 | H11: [Bull Case] R&D % of Revenue modeled at 13.5% of revenue in FY2031, gliding from 13.5% (FY2026 actual) toward 13.5% as the model assumes operating leverage improves EBITDA margin toward 28.2% by FY2031. Adjusted by -0.7% vs. Base Case.
A12: S&M % of Revenue | B12: 0.21833333 | C12: 0.21833333 | D12: 0.21833333 | E12: 0.21833333 | F12: 0.21833333 | H12: [Bull Case] S&M % of Revenue modeled at 22.5% of revenue in FY2031, gliding from 22.5% (FY2026 actual) toward 22.5% as the model assumes operating leverage improves EBITDA margin toward 28.2% by FY2031. Adjusted by -0.7% vs. Base Case.
A13: G&A % of Revenue | B13: 0.076333333 | C13: 0.076333333 | D13: 0.076333333 | E13: 0.076333333 | F13: 0.076333333 | H13: [Bull Case] G&A % of Revenue modeled at 8.3% of revenue in FY2031, gliding from 8.3% (FY2026 actual) toward 8.3% as the model assumes operating leverage improves EBITDA margin toward 28.2% by FY2031. Adjusted by -0.7% vs. Base Case.
A14: R&D | B14: =B8*B11 | C14: =C8*C11 | D14: =D8*D11 | E14: =E8*E11 | F14: =F8*F11
A15: S&M | B15: =B8*B12 | C15: =C8*C12 | D15: =D8*D12 | E15: =E8*E12 | F15: =F8*F12
A16: G&A | B16: =B8*B13 | C16: =C8*C13 | D16: =D8*D13 | E16: =E8*E13 | F16: =F8*F13
A17: Total Opex (ex D&A) | B17: =SUM(B14:B16) | C17: =SUM(C14:C16) | D17: =SUM(D14:D16) | E17: =SUM(E14:E16) | F17: =SUM(F14:F16)
A18: EBITDA | B18: =B10-B17 | C18: =C10-C17 | D18: =D10-D17 | E18: =E10-E17 | F18: =F10-F17
A19: EBITDA Margin % | B19: =IFERROR(B18/B8,0) | C19: =IFERROR(C18/C8,0) | D19: =IFERROR(D18/D8,0) | E19: =IFERROR(E18/E8,0) | F19: =IFERROR(F18/F8,0)
A20: D&A % of Revenue | B20: 0.0395 | C20: 0.0395 | D20: 0.0395 | E20: 0.0395 | F20: 0.0395 | H20: D&A modeled at the 4.0% historical average of revenue, held flat given no disclosed capex step-change.
A21: D&A | B21: =B8*B20 | C21: =C8*C20 | D21: =D8*D20 | E21: =E8*E20 | F21: =F8*F20
A22: EBIT | B22: =B18-B21 | C22: =C18-C21 | D22: =D18-D21 | E22: =E18-E21 | F22: =F18-F21
A23: EBIT Margin % | B23: =IFERROR(B22/B8,0) | C23: =IFERROR(C22/C8,0) | D23: =IFERROR(D22/D8,0) | E23: =IFERROR(E22/E8,0) | F23: =IFERROR(F22/F8,0)
A24: Tax Rate % | B24: 0.24 | C24: 0.24 | D24: 0.24 | E24: 0.24 | F24: 0.24 | H24: Tax rate held at the 24.0% historical average effective rate.
A25: Taxes on EBIT | B25: =MAX(B22,0)*B24 | C25: =MAX(C22,0)*C24 | D25: =MAX(D22,0)*D24 | E25: =MAX(E22,0)*E24 | F25: =MAX(F22,0)*F24
A26: NOPAT | B26: =B22-B25 | C26: =C22-C25 | D26: =D22-D25 | E26: =E22-E25 | F26: =F22-F25
A27: Capex % of Revenue | B27: 0.046166667 | C27: 0.04325 | D27: 0.040333333 | E27: 0.037416667 | F27: 0.0345 | H27: [Bull Case] Capex modeled at 4.0% of revenue in FY2031, gliding from the 5.1% recent historical average (vs. 4.8% in the most recent year) toward 4.0% - the historical D&A % of revenue - by FY2031, reflecting the standard DCF assumption that reinvestment normalizes to roughly track depreciation once the business settles into the stable long-run growth priced into the terminal value. Adjusted by -0.5% vs. Base Case.
A28: Capex | B28: =B8*B27 | C28: =C8*C27 | D28: =D8*D27 | E28: =E8*E27 | F28: =F8*F27
A29: NWC % of Revenue | B29: 0.095583333 | C29: 0.095583333 | D29: 0.095583333 | E29: 0.095583333 | F29: 0.095583333 | H29: [Bull Case] Net working capital modeled at the 10.1% historical average of revenue, held constant given no evidence of a structural change in payment terms. Adjusted by -0.5% vs. Base Case.
A30: Net Working Capital | B30: =B8*B29 | C30: =C8*C29 | D30: =D8*D29 | E30: =E8*E29 | F30: =F8*F29
A31: Change in NWC | B31: =B30-'Historical BS'!G$27 | C31: =C30-B30 | D31: =D30-C30 | E31: =E30-D30 | F31: =F30-E30
A32: FCFF = NOPAT + D&A − Capex − ΔNWC | B32: =B26+B21-B28-B31 | C32: =C26+C21-C28-C31 | D32: =D26+D21-D28-D31 | E32: =E26+E21-E28-E31 | F32: =F26+F21-F28-F31
A33: Discount Period (n) | B33: 1 | C33: 2 | D33: 3 | E33: 4 | F33: 5
A34: Discount Factor = 1/(1+WACC)^n | B34: =1/(1+$B$4)^B33 | C34: =1/(1+$B$4)^C33 | D34: =1/(1+$B$4)^D33 | E34: =1/(1+$B$4)^E33 | F34: =1/(1+$B$4)^F33
A35: PV of FCFF | B35: =B32*B34 | C35: =C32*C34 | D35: =D32*D34 | E35: =E32*E34 | F35: =F32*F34

Sheet DCF (Bull)
A1: Discounted Cash Flow - Bull Case
A3: Sum of PV of Explicit-Period FCFF | B3: =SUMPRODUCT('Forecast & FCFF (Bull)'!B32:F32,'Forecast & FCFF (Bull)'!B34:F34)
A4: Base-Case Terminal g (live link) + Scenario Delta | B4: ='DCF (Base)'!$B$4+(0.005)
A5: Terminal FCFF = Final-Year FCFF × (1+g) | B5: ='Forecast & FCFF (Bull)'!F32*(1+B4)
A6: Terminal Value (Gordon Growth) = TFCFF/(WACC−g) | B6: =B5/('Forecast & FCFF (Bull)'!$B$4-B4)
A7: PV of Terminal Value | B7: =B6*'Forecast & FCFF (Bull)'!F34
A8: Enterprise Value | B8: =B3+B7
A9: Terminal Value % of Enterprise Value | B9: =IFERROR(B7/B8,0)
A10: Exit Multiple (x EBITDA, cross-check) | B10: 14
A11: Terminal Value (Exit Multiple, memo) | B11: ='Forecast & FCFF (Bull)'!F18*B10
A13: Enterprise Value → Equity Value Bridge
A14: Enterprise Value | B14: =B8
A15: + Cash & Investments | B15: 869.5718
A16: − Total Debt | B16: -215
A17: − Lease Liabilities | B17: -40
A18: − Minority Interest | B18: 0
A19: − Preferred Stock | B19: 0
A20: Equity Value | B20: =B14+SUM(B15:B19)
A21: Diluted Shares Outstanding | B21: 115
A22: Equity Value per Share | B22: =IFERROR(B20/B21,0)
A23: Current Share Price | B23: 62.5
A24: Upside / (Downside) % | B24: =IFERROR(B22/B23-1,0)

Sheet Scenario Summary
A1: Scenario Summary
A3: Scenario | B3: Value/Share | C3: Current Price | D3: Upside/(Downside) | E3: Enterprise Value | F3: Equity Value | G3: WACC | H3: Terminal Growth | I3: % EV from TV
A4: Bear | B4: ='DCF (Bear)'!B22 | C4: ='DCF (Bear)'!B23 | D4: ='DCF (Bear)'!B24 | E4: ='DCF (Bear)'!B8 | F4: ='DCF (Bear)'!B20 | G4: ='Forecast & FCFF (Bear)'!$B$4 | H4: ='DCF (Bear)'!B4 | I4: =IFERROR('DCF (Bear)'!B7/'DCF (Bear)'!B8,0)
A5: Base | B5: ='DCF (Base)'!B22 | C5: ='DCF (Base)'!B23 | D5: ='DCF (Base)'!B24 | E5: ='DCF (Base)'!B8 | F5: ='DCF (Base)'!B20 | G5: =WACC!$B$17 | H5: ='DCF (Base)'!B4 | I5: =IFERROR('DCF (Base)'!B7/'DCF (Base)'!B8,0)
A6: Bull | B6: ='DCF (Bull)'!B22 | C6: ='DCF (Bull)'!B23 | D6: ='DCF (Bull)'!B24 | E6: ='DCF (Bull)'!B8 | F6: ='DCF (Bull)'!B20 | G6: ='Forecast & FCFF (Bull)'!$B$4 | H6: ='DCF (Bull)'!B4 | I6: =IFERROR('DCF (Bull)'!B7/'DCF (Bull)'!B8,0)

Sheet Sensitivity
A1: Sensitivity - Enterprise Value: WACC × Terminal Growth (Base Case)
A2: Fully formula-driven: re-discounts the Base Case's own explicit FCFF at each row's WACC, and grows the final year's FCFF at each column's g for the terminal value, the same construction as the DCF (Base) tab.
A5: WACC \ g | B5: 0.02 | C5: 0.025 | D5: 0.03 | E5: 0.035 | F5: 0.04
A6: 0.093154152 | B6: =IFERROR(SUMPRODUCT('Forecast & FCFF (Base)'!B29:F29,1/(1+$A6)^'Forecast & FCFF (Base)'!B30:F30)+('Forecast & FCFF (Base)'!F29*(1+B$5))/($A6-B$5)/(1+$A6)^'Forecast & FCFF (Base)'!F30,"") | C6: =IFERROR(SUMPRODUCT('Forecast & FCFF (Base)'!B29:F29,1/(1+$A6)^'Forecast & FCFF (Base)'!B30:F30)+('Forecast & FCFF (Base)'!F29*(1+C$5))/($A6-C$5)/(1+$A6)^'Forecast & FCFF (Base)'!F30,"") | D6: =IFERROR(SUMPRODUCT('Forecast & FCFF (Base)'!B29:F29,1/(1+$A6)^'Forecast & FCFF (Base)'!B30:F30)+('Forecast & FCFF (Base)'!F29*(1+D$5))/($A6-D$5)/(1+$A6)^'Forecast & FCFF (Base)'!F30,"") | E6: =IFERROR(SUMPRODUCT('Forecast & FCFF (Base)'!B29:F29,1/(1+$A6)^'Forecast & FCFF (Base)'!B30:F30)+('Forecast & FCFF (Base)'!F29*(1+E$5))/($A6-E$5)/(1+$A6)^'Forecast & FCFF (Base)'!F30,"") | F6: =IFERROR(SUMPRODUCT('Forecast & FCFF (Base)'!B29:F29,1/(1+$A6)^'Forecast & FCFF (Base)'!B30:F30)+('Forecast & FCFF (Base)'!F29*(1+F$5))/($A6-F$5)/(1+$A6)^'Forecast & FCFF (Base)'!F30,"")
A7: 0.098154152 | B7: =IFERROR(SUMPRODUCT('Forecast & FCFF (Base)'!B29:F29,1/(1+$A7)^'Forecast & FCFF (Base)'!B30:F30)+('Forecast & FCFF (Base)'!F29*(1+B$5))/($A7-B$5)/(1+$A7)^'Forecast & FCFF (Base)'!F30,"") | C7: =IFERROR(SUMPRODUCT('Forecast & FCFF (Base)'!B29:F29,1/(1+$A7)^'Forecast & FCFF (Base)'!B30:F30)+('Forecast & FCFF (Base)'!F29*(1+C$5))/($A7-C$5)/(1+$A7)^'Forecast & FCFF (Base)'!F30,"") | D7: =IFERROR(SUMPRODUCT('Forecast & FCFF (Base)'!B29:F29,1/(1+$A7)^'Forecast & FCFF (Base)'!B30:F30)+('Forecast & FCFF (Base)'!F29*(1+D$5))/($A7-D$5)/(1+$A7)^'Forecast & FCFF (Base)'!F30,"") | E7: =IFERROR(SUMPRODUCT('Forecast & FCFF (Base)'!B29:F29,1/(1+$A7)^'Forecast & FCFF (Base)'!B30:F30)+('Forecast & FCFF (Base)'!F29*(1+E$5))/($A7-E$5)/(1+$A7)^'Forecast & FCFF (Base)'!F30,"") | F7: =IFERROR(SUMPRODUCT('Forecast & FCFF (Base)'!B29:F29,1/(1+$A7)^'Forecast & FCFF (Base)'!B30:F30)+('Forecast & FCFF (Base)'!F29*(1+F$5))/($A7-F$5)/(1+$A7)^'Forecast & FCFF (Base)'!F30,"")
A8: 0.10315415 | B8: =IFERROR(SUMPRODUCT('Forecast & FCFF (Base)'!B29:F29,1/(1+$A8)^'Forecast & FCFF (Base)'!B30:F30)+('Forecast & FCFF (Base)'!F29*(1+B$5))/($A8-B$5)/(1+$A8)^'Forecast & FCFF (Base)'!F30,"") | C8: =IFERROR(SUMPRODUCT('Forecast & FCFF (Base)'!B29:F29,1/(1+$A8)^'Forecast & FCFF (Base)'!B30:F30)+('Forecast & FCFF (Base)'!F29*(1+C$5))/($A8-C$5)/(1+$A8)^'Forecast & FCFF (Base)'!F30,"") | D8: =IFERROR(SUMPRODUCT('Forecast & FCFF (Base)'!B29:F29,1/(1+$A8)^'Forecast & FCFF (Base)'!B30:F30)+('Forecast & FCFF (Base)'!F29*(1+D$5))/($A8-D$5)/(1+$A8)^'Forecast & FCFF (Base)'!F30,"") | E8: =IFERROR(SUMPRODUCT('Forecast & FCFF (Base)'!B29:F29,1/(1+$A8)^'Forecast & FCFF (Base)'!B30:F30)+('Forecast & FCFF (Base)'!F29*(1+E$5))/($A8-E$5)/(1+$A8)^'Forecast & FCFF (Base)'!F30,"") | F8: =IFERROR(SUMPRODUCT('Forecast & FCFF (Base)'!B29:F29,1/(1+$A8)^'Forecast & FCFF (Base)'!B30:F30)+('Forecast & FCFF (Base)'!F29*(1+F$5))/($A8-F$5)/(1+$A8)^'Forecast & FCFF (Base)'!F30,"")
A9: 0.10815415 | B9: =IFERROR(SUMPRODUCT('Forecast & FCFF (Base)'!B29:F29,1/(1+$A9)^'Forecast & FCFF (Base)'!B30:F30)+('Forecast & FCFF (Base)'!F29*(1+B$5))/($A9-B$5)/(1+$A9)^'Forecast & FCFF (Base)'!F30,"") | C9: =IFERROR(SUMPRODUCT('Forecast & FCFF (Base)'!B29:F29,1/(1+$A9)^'Forecast & FCFF (Base)'!B30:F30)+('Forecast & FCFF (Base)'!F29*(1+C$5))/($A9-C$5)/(1+$A9)^'Forecast & FCFF (Base)'!F30,"") | D9: =IFERROR(SUMPRODUCT('Forecast & FCFF (Base)'!B29:F29,1/(1+$A9)^'Forecast & FCFF (Base)'!B30:F30)+('Forecast & FCFF (Base)'!F29*(1+D$5))/($A9-D$5)/(1+$A9)^'Forecast & FCFF (Base)'!F30,"") | E9: =IFERROR(SUMPRODUCT('Forecast & FCFF (Base)'!B29:F29,1/(1+$A9)^'Forecast & FCFF (Base)'!B30:F30)+('Forecast & FCFF (Base)'!F29*(1+E$5))/($A9-E$5)/(1+$A9)^'Forecast & FCFF (Base)'!F30,"") | F9: =IFERROR(SUMPRODUCT('Forecast & FCFF (Base)'!B29:F29,1/(1+$A9)^'Forecast & FCFF (Base)'!B30:F30)+('Forecast & FCFF (Base)'!F29*(1+F$5))/($A9-F$5)/(1+$A9)^'Forecast & FCFF (Base)'!F30,"")
A10: 0.11315415 | B10: =IFERROR(SUMPRODUCT('Forecast & FCFF (Base)'!B29:F29,1/(1+$A10)^'Forecast & FCFF (Base)'!B30:F30)+('Forecast & FCFF (Base)'!F29*(1+B$5))/($A10-B$5)/(1+$A10)^'Forecast & FCFF (Base)'!F30,"") | C10: =IFERROR(SUMPRODUCT('Forecast & FCFF (Base)'!B29:F29,1/(1+$A10)^'Forecast & FCFF (Base)'!B30:F30)+('Forecast & FCFF (Base)'!F29*(1+C$5))/($A10-C$5)/(1+$A10)^'Forecast & FCFF (Base)'!F30,"") | D10: =IFERROR(SUMPRODUCT('Forecast & FCFF (Base)'!B29:F29,1/(1+$A10)^'Forecast & FCFF (Base)'!B30:F30)+('Forecast & FCFF (Base)'!F29*(1+D$5))/($A10-D$5)/(1+$A10)^'Forecast & FCFF (Base)'!F30,"") | E10: =IFERROR(SUMPRODUCT('Forecast & FCFF (Base)'!B29:F29,1/(1+$A10)^'Forecast & FCFF (Base)'!B30:F30)+('Forecast & FCFF (Base)'!F29*(1+E$5))/($A10-E$5)/(1+$A10)^'Forecast & FCFF (Base)'!F30,"") | F10: =IFERROR(SUMPRODUCT('Forecast & FCFF (Base)'!B29:F29,1/(1+$A10)^'Forecast & FCFF (Base)'!B30:F30)+('Forecast & FCFF (Base)'!F29*(1+F$5))/($A10-F$5)/(1+$A10)^'Forecast & FCFF (Base)'!F30,"")
A13: Ranked Valuation Drivers (EV swing %, full model re-run per shift; see Sources & Notes)
A14: Driver | B14: EV Swing %
A15: WACC (+/-1.0pp) | B15: 0.28728246
A16: Terminal Growth (+/-0.5pp) | B16: 0.10806834
A17: Terminal EBITDA Margin (+/-1.0pp) | B17: 0.085460768
A18: Revenue CAGR (+/-1.0pp/yr) | B18: 0.071502898
A19: Capex % of Revenue (+/-0.5pp) | B19: 0.05622419

Sheet Sources & Notes
A1: Sources & Notes
A3: Methodology
A4: Enterprise value is built as an unlevered Free Cash Flow to Firm (FCFF) DCF: FCFF = NOPAT + D&A − Capex − Change in NWC, discounted at WACC (CAPM cost of equity + after-tax cost of debt, weighted by market value of equity and debt).
A5: Terminal value uses the Gordon Growth perpetuity, Terminal FCFF / (WACC − g), discounted back at the same WACC and same convention as the explicit-period cash flows; an EBITDA exit-multiple value is shown alongside as a cross-check only, not used in the primary Enterprise Value.
A6: COGS/operating-expense line items from automated data sources are not always independently broken out; where that is the case, EBITDA/EBIT/Pre-Tax/Net Income are the source's own reported figures, with the Revenue-to-EBITDA gap allocated to a single combined opex line (see the Historical IS tab).
A7: Historical Balance Sheet 'Other Assets'/'Other Liabilities' are residual (plug) figures computed against the source's own reported Total Assets/Total Liabilities, so every historical year ties out exactly to Assets = Liabilities + Equity (see the Balance Check row on the Historical BS tab).
A8: Bear/Bull scenarios shift revenue growth, margins, capex/NWC intensity, WACC, and terminal growth from the Base Case by fixed deltas (see each scenario's own Forecast & FCFF tab for its inputs and rationale) rather than being independently re-derived from source data.
A9: The Sensitivity and Value-Driver Ranking figures are produced by fully re-running this Python model with one assumption shifted at a time (not a linear approximation); the WACC × Growth grid on the Sensitivity tab is reproduced as a live Excel formula, while the driver-ranking swings for drivers outside that 2-D grid (revenue growth, margin, capex) are pasted from that Python re-run.
A11: Data Ingestion Notes
A12: This model was built from a sample company or manually entered data: no automated data-source notes apply.
